{
  "blog_cp_manage_group_userbit": "3418", 
  "vbppb_delete": "5535", 
  "pm_editfolders": "4777", 
  "modifyusergroups_nonmemberbit": "4735", 
  ".tborder": "5465", 
  "modifyusergroups_displaybit": "4731", 
  "userfield_optional_input": "4971", 
  "formwidth": "5477", 
  "blog_entry_attachment": "3436", 
  "bbcode_quote_printable": "4548", 
  "forumhome_event": "4608", 
  "socialgroups_manage": "4880", 
  "blog_tag_cloud_link": "3511", 
  "postbit_ignore_global": "4812", 
  "blog_cp_manage_group_permbit": "3417", 
  "navbar_mini": "3601", 
  "picturecomment_message_moderatedview": "4774", 
  "postbit_modtools": "4401", 
  "contactus": "5002", 
  "album_edit": "4525", 
  "editor_jsoptions_size": "4583", 
  "modifyavatar_category": "4709", 
  "socialgroups_message_deleted": "4885", 
  "cyb_areg_manage": "4394", 
  "blog_cp_manage_subscriptions": "3421", 
  "blog_entry_editor_draft": "3445", 
  "ada_postbit_comment": "4274", 
  "editor_clientscript": "4580", 
  "spam_hammer_service_statistics_3_x": "5308", 
  "postbit_wrapper": "4818", 
  "vbppt_paynow": "5431", 
  "memberlist_search_select": "4690", 
  "threadadmin_easyspam": "4936", 
  "memberinfo_block_visitormessaging": "4661", 
  "faqbit": "4600", 
  "forumdisplay_sortarrow": "4605", 
  "forumhome_subforumbit_post": "4618", 
  "socialgroups_picturebit": "4894", 
  "EZsociallinks_mitab_bits": "833", 
  "moderation_picturebit": "4697", 
  "blog_member_css": "3473", 
  "blog_manage_attachmentbit": "3469", 
  "calendar_monthly_birthday": "4559", 
  "navbar_usercp_menu": "747", 
  "socialgroups_accepttransfer": "4858", 
  "threadadmin_moveposts": "4954", 
  "modifyusergroups_groupleader": "4732", 
  "moderation_pictures": "4699", 
  "vbvua_addon_list": "5033", 
  "usercp_newvisitormessagebit": "4967", 
  "newpost_quote": "4753", 
  "vbseo_likeshare": "5161", 
  "post_thanks_memberinfo_block": "791", 
  "newpost_threadmanage": "4754", 
  "memberlist_search_select_multiple": "4691", 
  "navbar_google_search": "2798", 
  "modifyavatarbit_custom": "4707", 
  "socialgroups_groupsub_bit": "4879", 
  "announcement_edit": "4540", 
  "tablewidth": "4506", 
  "memberinfo_visitorbit": "4677", 
  "subscription_payment_worldpay": "4918", 
  "postbit_automoderated": "4808", 
  "pollresults": "4801", 
  "blog_rules": "3485", 
  "im_send_msn": "4641", 
  "postbit_attachment": "4804", 
  "register_coppaform": "4829", 
  "body": "5471", 
  "pm_editfolderbit": "4776", 
  "vbvua_page_corner_rl": "5034", 
  "modifyattachmentsbit": "4704", 
  "formspacer": "5476", 
  "subscribe_choosetype": "4902", 
  ".vbmenu_option": "5442", 
  "socialgroups_owngroup_bit": "4892", 
  "modifyavatarbit_noavatar": "4708", 
  "moderation_groupdiscussions": "4695", 
  "vbppb_textad": "5542", 
  "legend": "5444", 
  "blog_entry_ignore": "3449", 
  "memberinfo_block_ministats": "4656", 
  "pm_messagelist": "5506", 
  "help_avatars_category": "4623", 
  "THREADADMIN": "4930", 
  "EXTRA": "5566", 
  "socialgroups_pictures": "4895", 
  "cyb_areg_manageinv_bit": "4397", 
  "post_thanks_box": "787", 
  "blog_show_entry": "5206", 
  "BLOG": "3563", 
  "forum_searchtags": "5572", 
  "help_bbcodes_link": "4627", 
  "htmlextrasfolder": "4491", 
  "socialgroups_grouplist_bit": "728", 
  "modifyusergroups_joinrequestbit": "4733", 
  "imgdir_attach": "5479", 
  "ad_footer_end": "4511", 
  "blog_entry_editor_preview": "3446", 
  "tag_edit_ajax": "5518", 
  "socialgroups_overview": "4891", 
  "vbppt_promote": "5564", 
  "modifyprofilepic": "4719", 
  "blog_cp_modify_options": "3426", 
  "postbit_attachmentimage": "5511", 
  "threadadmin_easyspam_confirm": "4938", 
  "FORUMDISPLAY": "5494", 
  "im_yahoo": "4645", 
  "select": "5577", 
  "post_thanks_navbar_search": "793", 
  "socialgroups_discussion": "4869", 
  "blog_comment_ignore": "3405", 
  "forumhome_loggedinuser": "4614", 
  "forumhome_subforumseparator_post": "4620", 
  "vbseo_profile_menu": "5168", 
  "blog_sidebar_user": "3498", 
  "calendar_monthly_day_other": "4561", 
  "modifyusercss_backgroundbit": "4724", 
  "ad_blog_list_firstentry": "3387", 
  "memberinfo_tiny": "4675", 
  "humanverify_image": "5498", 
  "printthreadbit_ignore": "4827", 
  "blog_entry_profile": "3450", 
  "whosonlinebit": "4995", 
  "vbppb_thank_you": "5546", 
  "smiliepopup_row": "4854", 
  "blog_search_results": "3487", 
  "threadadmin_editthread": "4946", 
  "ad_showthread_firstpost_start": "4521", 
  "userinfraction_view": "4985", 
  ".highlight": "4460", 
  "editor_css": "4581", 
  "CALENDAR": "4551", 
  "cyb_areg_manageuser_bit": "4396", 
  "subscription": "4907", 
  "reputation_yourpost": "4836", 
  "editor_styles_button_down": "4589", 
  "messagewidth_blog": "3519", 
  "forumhome_forumbit_level2_post": "5497", 
  "vbpfts_rules_form": "5380", 
  "vbppt_new": "5569", 
  "vbseo_ui_headinc": "5169", 
  "moderation_groupmessages": "4696", 
  "modifyavatarbit": "4706", 
  "lostpw": "5017", 
  "kh99_password_policy": "5562", 
  "blog_navbar_search": "3478", 
  "search_results_postbit_lastvisit": "4840", 
  "editor_toolbar_on": "5492", 
  "threadadmin_easyspam_userbit": "4944", 
  "SUBSCRIBE": "4901", 
  "userfield_select": "4974", 
  "modifyoptions": "4714", 
  "imgdir_editor": "5481", 
  "imgdir_statusicon": "5486", 
  "newpost_errormessage": "4751", 
  "vbppfo_": "4374", 
  "smiliepopup_category": "4853", 
  "humanverify_question": "4633", 
  "calendar_edit_customfield": "4555", 
  "pm_messagelist_periodgroup": "4784", 
  "memberinfo_infractionbit": "4666", 
  "cyb_areg_manage_bit": "4395", 
  ".wysiwyg": "5470", 
  "editor_styles_menu_down": "4593", 
  "pm_messagelistbit_user": "4783", 
  "cellspacing": "5474", 
  "newreply": "5503", 
  ".vbmenu_hilite": "5441", 
  "picturecomment_message": "4770", 
  "picturecomment_commentarea": "4765", 
  "blog_comment_deleted": "3403", 
  "pagenav_pagelink": "4763", 
  "blog_inlinemod_delete_profile_comments": "3461", 
  "ad_showthread_firstpost_sig": "4520", 
  "pm_receiptsbit": "4791", 
  "vbppt_paymentapi_form": "5430", 
  "printthreadbit": "4826", 
  "postbit_reputation": "4817", 
  "postbit_external": "4810", 
  "newpoll": "4747", 
  "memberinfo_block_infractions": "4655", 
  "footer": "5575", 
  "register": "5512", 
  "blog_list_entries": "3468", 
  "memberinfo_block_statistics": "4660", 
  "blog_list_blogs_all": "3463", 
  "help_rules": "4628", 
  "moderation_posts": "4700", 
  "socialgroups_mygroups_bit": "4887", 
  "STANDARD_BETTER_ERROR": "760", 
  "contactus_option": "5003", 
  "calendar_showeventsbit": "4570", 
  "blog_member_ministats": "3474", 
  "im_icq": "4636", 
  "newreply_reviewbit_ignore": "4758", 
  "blog_blogpost_quote": "3399", 
  "album_addgroup": "4523", 
  "blog_cp_manage_categories_category": "3409", 
  "FAQ": "5493", 
  "editor_styles_popup_down": "4596", 
  "showthread_changepostsowner_link": "3599", 
  "ap_groupmessage_pop_bit": "726", 
  "picturecomment_form": "4769", 
  "editor_styles_button_hover": "4590", 
  "memberinfo_block_friends_mini": "4653", 
  "bbcode_quote": "4547", 
  "blog_cp_manage_group": "3413", 
  "blog_cp_new_category": "3429", 
  "blog_reportitem": "3484", 
  "postbit_deleted": "4809", 
  "socialgroups_editor": "4874", 
  "printthread": "4825", 
  "register_verify_age": "4831", 
  "subscription_payment_nochex": "4916", 
  ".tfoot": "5467", 
  "threadadmin_easyspam_skipped_prune": "4943", 
  "album_picturelist": "4532", 
  "socialgroups_discussion_ignored": "4872", 
  "modifybuddylist_user": "4711", 
  "textareacols_ie4": "4507", 
  "blog_cp_manage_group_perm": "3416", 
  "forumhome_markread_script": "4615", 
  "ad_showthread_beforeqr": "4518", 
  "pollresults_table": "5509", 
  "blog_sidebar_user_block_search": "3504", 
  "sendtofriend": "5022", 
  "picturecomment_css": "4766", 
  "blog_comment_editor": "3404", 
  "userfield_checkbox_option": "4970", 
  "userfield_wrapper": "4979", 
  "vbppb_paymentapi_form": "5541", 
  "blog_member_comment_deleted": "3472", 
  "memberlist": "4682", 
  "modifyusercss_headinclude": "4729", 
  ".time": "645", 
  "JOINREQUESTS": "5014", 
  "blog_sidebar_user_block_tagcloud": "3505", 
  "socialgroups_addpicture_invalidurl": "4860", 
  "postbit_onlinestatus": "4815", 
  "blog_cp_manage_group_blogbit": "3414", 
  "FORUMDISPLAY_Separate2": "749", 
  ".inlinemod": "4461", 
  ".panel": "5463", 
  "postbit_legacy": "2207", 
  "calendar_smallmonth_day_other": "4573", 
  "vbppb_paybutton_bit": "5538", 
  "memberlist_search_radio": "4689", 
  "vbppfo_info_bit": "4370", 
  "vbppb_textad_container": "4303", 
  "blog_sidebar_user_block_category": "3500", 
  "SOCIALGROUPS": "727", 
  "modifyusergroups": "4730", 
  "ad_forumhome_afterforums": "4514", 
  "pollnewbit": "4795", 
  "editor_toolbar_off": "4597", 
  "socialgroups_subscriptions": "4899", 
  "threadadmin_deleteposts": "5210", 
  "socialgroups_categorylist": "4863", 
  "threadadmin_authenticate": "4931", 
  "help_bbcodes_bbcode": "4626", 
  "reputation_ajax": "4834", 
  "blog_postbit_entries_link": "3483", 
  "subscription_payment_moneybookers": "4915", 
  ".panelsurround": "5464", 
  "memberlist_search_optional_input": "4688", 
  "postbit_quickedit": "4816", 
  "calendar_reminder_eventbit": "4567", 
  "threadbit_deleted": "4960", 
  "calendar_weekly_day": "4577", 
  "ad_header_logo": "4516", 
  "blog_postbit_blog_this_post": "3482", 
  "showthread_quickreply": "782", 
  "userfield_textarea": "4977", 
  "posthistory_content_not_changed": "4821", 
  "reportitem": "5526", 
  "forumhome_forumbit_level1_post": "5212", 
  "MEMBERINFO": "5499", 
  "blog_cp_manage_custompage_bit": "3411", 
  "SHOWGROUPS": "4841", 
  "ad_header_end": "4515", 
  "memberinfo_visitormessage_global_ignored": "4680", 
  "ada_postbit_flipped": "4275", 
  "codeblockwidth": "5475", 
  "blog_tagbit": "3508", 
  "calendarjump": "4552", 
  "usernote": "4986", 
  "humanverify_recaptcha": "5567", 
  "blog_css": "3432", 
  "moderation_deletepictures": "4693", 
  "help_avatars": "4621", 
  "blog_bbcode_code": "3395", 
  "blog_list_blogs_blog_ignore": "3466", 
  "navbar": "5502", 
  "tag_cloud_page": "4925", 
  "postbit_ip": "4813", 
  "blog_sidebar_user_block_entries": "3503", 
  "blog_cp_manage_trackbacks": "3423", 
  "help_avatars_row": "4624", 
  "album_latestbit": "4526", 
  "bbcode_code_printable": "4542", 
  "editor_smiliebox": "4585", 
  "blog_member_stats": "3475", 
  "threadadmin_movethread": "4955", 
  "blog_cp_manage_categories": "3408", 
  "blog_notify_urls_url": "3480", 
  "ad_navbar_below": "4517", 
  "picturecomment_message_global_ignored": "4772", 
  "blog_cp_manage_custom_editor": "3412", 
  "mailform": "5018", 
  "register_rules": "4830", 
  "visitormessage_editor": "4988", 
  "STANDARD_ERROR_LITE": "5027", 
  "ad_footer_start": "4512", 
  "socialgroups_confirm": "4866", 
  "vbppt_thank_you": "5434", 
  "cyb_apboupc_globalset_currbit": "1523", 
  "blog_custompage": "3433", 
  "pollpreview": "4799", 
  "album_picturebit_checkbox": "4530", 
  "memberinfo_visitormessage": "4678", 
  "ad_blog_showentry_after": "3388", 
  "modifyavatar": "4705", 
  "editpost": "3583", 
  "blog_usercss": "3516", 
  "joinrequestsbit": "5015", 
  "option": "5020", 
  "messagewidth_usercp": "5488", 
  "memberinfo_socialgroupbit_text": "4674", 
  "vbpwr_": "5233", 
  "album_picture_edit": "4534", 
  "threadadmin_mergethread": "4952", 
  "blog_entry_editor_attachment": "3442", 
  "titleimage": "5491", 
  "formwidth_usercp": "5478", 
  "modifyattachments": "4703", 
  "post_thanks_javascript": "790", 
  "pm_emptyfolder": "4778", 
  "blog_tag_edit": "3512", 
  "blog_member_block": "3471", 
  "calendar_reminder_choosetype": "4566", 
  "usercp_groupinvitebit": "4965", 
  "blog_home": "3455", 
  "editor_smilie": "4584", 
  "board_inactive_warning": "5001", 
  "socialgroups_subscribe_group": "4898", 
  "vbppb_error_bit": "5536", 
  "calendar_smallmonth_header": "4574", 
  "vbseo_linkbackmenu": "5165", 
  "threadadmin_easyspam_user_option": "4945", 
  "socialgroups_discussion_deleted": "4871", 
  "textareacols_ns4": "4508", 
  "visitormessage_simpleview_deleted": "4991", 
  "search_results": "5515", 
  "im_aim": "4635", 
  "socialgroups_discussion_quickedit": "4873", 
  "ad_forumdisplay_afterthreads": "4513", 
  "blog_cp_manage_sidebar": "3419", 
  "memberinfo_membergroupbit": "4667", 
  "vbphelper_user_details_form_3": "5360", 
  "bbcode_html": "4543", 
  "forumhome_forumbit_level1_nopost": "5496", 
  ".alt2, .alt2Active": "5461", 
  "modifyprivacy_bit": "4717", 
  "USERCP": "4963", 
  "showthread_similarthreadbit": "4850", 
  "blog_entry_editor": "3441", 
  "calendar_monthly_event": "4562", 
  "memberlist_search_textbox": "4692", 
  "blog_cp_modify_profile_preview": "3428", 
  "threadadmin_deletethread": "5209", 
  "blog_cp_manage_sidebar_bit": "3420", 
  "threadadmin_logbit": "4949", 
  "STANDARD_REDIRECT": "687", 
  "forumhome_vietvbb_com_adv": "3520", 
  "forumhome_vbo": "4202", 
  "newpost_preview": "4752", 
  "blog_cp_manage_usercss": "3425", 
  "newpost_disablesmiliesoption": "4750", 
  "modifypassword": "4716", 
  "cyb_areg_edit": "4398", 
  "memberinfo_usercss": "4676", 
  "imgdir_button": "5480", 
  "blog_tag_cloud": "3509", 
  "pm_messagelistbit": "4781", 
  "posthistory_content_changed": "4820", 
  "socialgroups_category_cloud_bit": "4865", 
  "blog_entry_editor_attachments": "3443", 
  "forumhome_forumbit_level2_nopost": "5215", 
  "blog_entry_attachment_thumbnail": "3438", 
  "help_smilies_category": "4630", 
  "gobutton": "5011", 
  "modifyprofileprivacy": "4720", 
  "kh99_password_rule": "5563", 
  "threadadmin_deletethreads": "5211", 
  "post_thanks_box_bit": "788", 
  "memberinfo_block_groups": "4654", 
  "im_skype": "4644", 
  "blog_comment": "3402", 
  "reputation": "4832", 
  "forumhome_birthdaybit": "4607", 
  "threadadmin_easyspam_ip_option": "4942", 
  "blog_sidebar_generic": "3497", 
  "blog_sidebar_calendar_day": "3492", 
  "newattachmentbit": "4744", 
  "vbppb_banner_bit": "5382", 
  "STANDARD_ERROR": "5527", 
  "calendar_showevents": "4569", 
  "vbppfo_info_wrapper": "4369", 
  "memberinfo_ModTools": "4400", 
  ".vbmenu_popup": "661", 
  "searchtagbit": "5571", 
  "modifyoptions_timezone": "4715", 
  "blog_inlinemod_delete_comments": "3459", 
  "help_smilies_smilie": "4631", 
  ".vbmenu_control": "5469", 
  "tag_edit": "5517", 
  "vbppb_add": "5531", 
  "newattachment": "4743", 
  "blog_edit_trackback": "3434", 
  "pagenav_pagelinkrel": "4764", 
  "memberlist_resultsbit_field": "4685", 
  "vbphelper_transaction_list_3": "5358", 
  "memberinfo_imbit": "4665", 
  "album_picture_uploadbit": "4537", 
  "blog_inlinemod_delete_entries": "3460", 
  "blog_entry": "3435", 
  "userinfraction_infobit": "4984", 
  "threadadmin_imod_menu_thread": "4948", 
  "pagenav": "5505", 
  "calendar_edit": "4554", 
  "ad_blog_sidebar_end": "3391", 
  "blog_cp_stats": "3431", 
  "subscription_payment_paypal": "4917", 
  "blog_cp_manage_group_join": "3415", 
  "modifybuddylist": "4710", 
  "modifyusergroups_requesttojoin": "4736", 
  "blog_notify_urls": "3479", 
  "navbar_noticebit": "4741", 
  "blog_sidebar_user_block_archive": "3499", 
  "optgroup": "5019", 
  "pm_messagelistbit_ignore": "4782", 
  "memberinfo_deletemessages": "4664", 
  "blog_sidebar_user_block_visitors": "3506", 
  "forumdisplay_changethreadsowner": "3600", 
  "blog_cp_manage_custompage": "3410", 
  "blog_cp_css": "3407", 
  "calendar_monthly_header": "4563", 
  "picturecomment_message_ignored": "4773", 
  "tag_search": "4929", 
  "calendar_showbirthdays": "4568", 
  "post_thanks_button": "789", 
  "ad_blog_showentry_firstcomment": "3390", 
  "post_thanks_member_info": "792", 
  "navbar_link": "4740", 
  "editpoll": "5005", 
  "editor_styles_menu_normal": "4595", 
  "calendar_monthly": "4558", 
  "userinfraction_banbit": "4982", 
  "help_smilies": "4629", 
  "blog_entry_external": "3447", 
  ".fjdpth2": "4456", 
  ".fjdpth3": "4457", 
  ".fjdpth0": "4454", 
  ".fjdpth1": "4455", 
  "userfield_select_multiple": "4975", 
  ".fjdpth4": "4458", 
  "EZsociallinks_postbit_bit": "4201", 
  "album_list": "4527", 
  "spam_hammer_service_runonce_js": "5306", 
  "socialgroups_addpicture_messagebit": "4861", 
  "pm_receipts": "4790", 
  "tag_cloud_headinclude": "4923", 
  "blog_trackback": "3514", 
  "threadadmin_easyspam_infraction": "4940", 
  "blog_home_list_blog": "779", 
  "polloption_multiple": "4798", 
  "pm_stopm": "5556", 
  "subscription_payment_2checkout": "4912", 
  "whosonline_resolveip": "4996", 
  "smiliepopup_smilie": "4855", 
  "reputationbit": "5513", 
  "memberinfo_block_recentvisitors": "4659", 
  "subscribe_move": "4905", 
  "memberinfo_profilefield": "4668", 
  "blog_header_custompage_link": "3454", 
  "memberlist_search": "4687", 
  "threadadmin_mergeposts": "4951", 
  "calendarjumpbit": "4553", 
  "post_thanks_postbit_legacy": "796", 
  "cyb_areg_invite": "4399", 
  "outerborderwidth": "4503", 
  "memberlist_resultsbit": "4684", 
  "vbppb_textads": "5545", 
  "WHOPOSTED": "4992", 
  "memberinfo_quickedit": "4671", 
  "polloptions_table": "4797", 
  "threadadmin_imod_menu_post": "4947", 
  "pm_popup_script": "4788", 
  "socialgroups_addpicture_messages": "4862", 
  "ad_blog_sidebar_start": "3393", 
  "blog_search_results_result": "3488", 
  "threadadmin_mergethreads": "4953", 
  "memberinfo_css": "5501", 
  "pm_trackpm": "4793", 
  "vbseo_help_linkback": "5159", 
  "forumhome_subforumbit_nopost": "4617", 
  "postbit_attachmentthumbnail": "4807", 
  "calendar_monthly_week": "4564", 
  "ad_blog_showentry_before": "3389", 
  "activateform": "4997", 
  "vbpwr_subscription_option_bit": "5234", 
  "FORUMHOME": "5495", 
  "editor_styles_menu_hover": "4594", 
  "blog_bookmark": "3401", 
  "memberinfo_visitormessage_ignored": "4681", 
  "subscription_paymentbit_payflow": "5369", 
  "messagewidth": "5487", 
  "textarea, .bginput": "5455", 
  "formwidth_blog": "3518", 
  "memberinfo_block_EZsociallinks_mitab": "834", 
  "FORUMDISPLAY_Separate": "748", 
  "header": "5576", 
  "modifyignorelist_user": "4713", 
  "albumbit": "4522", 
  "pagenav_curpage": "4762", 
  "subscription_payment": "4910", 
  "memberinfo_block_friends": "4652", 
  "ad_blog_sidebar_middle": "3392", 
  "newattachment_errormessage": "4745", 
  "calendar_monthly_day": "4560", 
  "album_moderatedcomments": "4528", 
  "imagesfolder": "4492", 
  "threadbit_announcement": "4959", 
  "blog_entry_editor_category": "3444", 
  "blog_send_to_friend": "3489", 
  "calendar_showeventsbit_customfield": "4571", 
  "blog_search_advanced": "3486", 
  "forumjump": "5523", 
  "bbcode_quote_styleid": -1, 
  "editor_styles_button_selected": "4592", 
  "blog_sidebar_entry_link": "3496", 
  "memberinfo_block_aboutme": "4649", 
  "blog_cp_manage_trackbacks_trackback": "3424", 
  "forumdisplay_moderator": "4604", 
  "pm_newpm": "5507", 
  "tag_cloud_box": "4921", 
  "vbppb_add_textad": "5532", 
  "picturecomment_deletemessages": "4767", 
  "pollresult": "5508", 
  "modifyusergroups_memberbit": "4734", 
  "subscription_activebit": "4908", 
  "posthistory_listbit": "4822", 
  "memberinfo_albumbit": "4647", 
  "showgroups_forumbit": "4842", 
  "visitormessage_simpleview": "4990", 
  "smiliepopup": "4852", 
  "vbpua_addon_template_tr": "5032", 
  "BUDDYLIST": "4549", 
  "editor_smiliebox_row": "4587", 
  "moderation_filter": "4694", 
  "subscribe_folderbit": "4904", 
  "spacer_open": "5419", 
  "socialgroups_newgroup_bit": "4889", 
  "socialgroups_css": "4867", 
  "vbseo_linkbacks": "5167", 
  "memberinfo_block": "5500", 
  "subscription_payment_authorizenet": "4913", 
  "vbppb_banner": "5533", 
  "GENERIC_SHELL": "5010", 
  "search_forums": "5514", 
  "vbseo_likebit": "5160", 
  "vbseo_linkbackmenu_entry": "5166", 
  "calendar_weekly_event": "4578", 
  "USERCP_SHELL": "5521", 
  "polloption": "4796", 
  "blog_cp_statbit": "3430", 
  "calendar_yearly": "4579", 
  "spam_hammer_service_statistics": "5307", 
  "memberinfo_profilefield_category": "4669", 
  "pm_nomessagehistory": "4787", 
  "blog_sidebar_calendar": "3491", 
  "bbcode_code": "4541", 
  "threadadmin_copyposts": "4932", 
  "blog_inlinemod_delete_trackbacks": "3462", 
  "socialgroups_search": "4896", 
  "blog_forumhome_stats": "3451", 
  "navbar_notifications_menubit": "4742", 
  "modifyuserlist_headinclude": "4738", 
  "threadbit_lastvisit": "4961", 
  "socialgroups_categorylist_bit": "4864", 
  "memberinfo_customfield_edit": "4663", 
  "newpost_usernamecode": "4755", 
  "blog_sidebar_custompage_link": "3495", 
  "vbppt_sticky": "5565", 
  "im_send_yahoo": "4643", 
  "threadbit": "5519", 
  "blog_bbcode_quote": "3398", 
  "imgdir_reputation": "5485", 
  "cyb_subforummanager": "3554", 
  "editor_smiliebox_straggler": "4588", 
  "threadadmin_easyspam_ipbit": "4941", 
  "tag_managebit": "4928", 
  "socialgroups_form": "4875", 
  "FORUMDISPLAY_Separate_top": "750", 
  "gtpm_messagelistbit": "3521", 
  "memberinfo_publicgroupbit": "4670", 
  "modifyusercss_error_link": "4728", 
  "newpost_attachmentbit": "4749", 
  "blog_postbit_blog_link": "3481", 
  "spacersize": "5490", 
  "vbseo_like_tree": "5163", 
  "socialgroups_mygroups_listview_bit": "4888", 
  "subscribe_confirm_delete": "4903", 
  "newreply_reviewbit_ignore_global": "4759", 
  "polleditbit": "4794", 
  "bbcode_php_styleid": -1, 
  "postbit_hiddenpics_bop5_vb4": "5208", 
  "postbit_hiddenpics_bop5_vb3": "5207", 
  "userinfractionbit": "4981", 
  "vbpcba_": "5179", 
  "picturecomment_preview": "4775", 
  "album_picture_editbit": "4535", 
  "ptpnt_buythread_form": "1516", 
  "tagbit": "4919", 
  "posthistory": "4819", 
  ".smallfont": "5452", 
  "modifyignorelist": "4712", 
  "vbppb_payment_confirmation": "5539", 
  "ad_showthread_firstpost": "3553", 
  "vbpua_addon_template": "5031", 
  "modifyusercss_bit": "4726", 
  ".navbar": "5451", 
  "blog_subscribe_to_item": "3507", 
  "tagbit_wrapper": "4920", 
  "threadadmin_managepost": "4950", 
  "posticonbit": "4823", 
  "blog_home_list_entry": "2206", 
  "socialgroups_subscribe": "4897", 
  "editor_jsoptions_font": "4582", 
  ".alt1, .alt1Active": "5460", 
  "usercp_reputationbits": "4968", 
  "bbcode_php": "4545", 
  "announcement": "4539", 
  "threadadmin_easyspam_headinclude": "4939", 
  "modifyuserlist_confirm": "4737", 
  "forumdisplay_loggedinuser": "4603", 
  "threadadmin_postbit": "4957", 
  "decimator_main": "3603", 
  ".button": "5578", 
  "moderation_picturecomments": "4698", 
  "im_send_skype": "4642", 
  "calendar_smallmonth_day": "4572", 
  "post_thanks_postbit_info": "795", 
  "userfield_radio": "4972", 
  "memberinfo_socialgroupbit": "4673", 
  "imgdir_misc": "5482", 
  "memberinfo_block_profilepicture": "4658", 
  "STANDARD_ERROR_LOGIN": "5028", 
  "forumhome_subforumseparator_nopost": "4619", 
  "socialgroups_managemembers": "4882", 
  "vbpppf_": "5372", 
  "cyb_apboupc_globalset": "1522", 
  "album_picturebit_unread": "4531", 
  "WHOSONLINE": "4994", 
  "CALENDAR_REMINDER": "4565", 
  "ATTACHMENTS": "5000", 
  "showthread_list": "4847", 
  "vbseo_likes_list_container": "5162", 
  "blog_list_blogs_best": "3464", 
  "userfield_select_option": "4976", 
  "threadadmin_movethreads": "4956", 
  "pm_showpm": "3602", 
  "memberinfo_block_contactinfo": "4651", 
  "album_addgroup_groupbit": "4524", 
  "moderation_threads": "4701", 
  "imgdir_rating": "5484", 
  "vbppb_viewall_textad": "5548", 
  "album_unreadcomments": "4538", 
  "blog_tag_edit_form": "3513", 
  "memberinfo_block_twitter": "746", 
  "shell_blank": "5023", 
  "blog_manage_attachments": "3470", 
  "userinfraction": "4980", 
  "activate_requestemail": "4998", 
  "modifysignature": "4722", 
  "socialgroups_addpictures": "4859", 
  "pm_filter": "4779", 
  "pm_movepm": "4785", 
  "blog_navbar_link_menu": "3527", 
  "modifyprofile": "4718", 
  "memberinfo_small": "4672", 
  "blog_sidebar_category_link": "3493", 
  "memberinfo_block_albums": "4650", 
  "postbit_quickdelete": "5558", 
  "forumhome_lastpostby": "4613", 
  "attachmentbit": "4999", 
  "showthread_similarthreads": "4851", 
  "picturecomment_message_deleted": "4771", 
  "usercp_referrals": "805", 
  ".alt3": "4452", 
  "smiliepopup_straggler": "4856", 
  "blog_bbcode_html": "3396", 
  "socialgroups_memberlist": "4883", 
  "moderation_visitormessages": "4702", 
  "calendar_weekly": "4576", 
  "usercp_nav_folderbit": "4966", 
  "showgroups_usergroupbit": "4844", 
  "editor_styles_button_normal": "4591", 
  "modifyusercss_backgroundrow": "4725", 
  ".tcat": "5466", 
  "td, th, p, li": "5454", 
  "vbppb_viewall": "5529", 
  "showthread_bookmarksite": "689", 
  "calendar_edit_recurrence": "4556", 
  "outertablewidth": "5489", 
  "blog_tag_cloud_box": "3510", 
  "socialgroups_groupmodlist_bit": "4878", 
  "lightbox": "5016", 
  "spam_hammer_service_js": "5305", 
  "angular_advertisement_css": "3594", 
  ".thead": "5468", 
  "threadbit_pagelink": "5520", 
  "vbpua_addon_template_table": "5030", 
  "socialgroups_deletemessages": "4868", 
  "threadadmin_easyspam_ban": "4937", 
  "blog_entry_featured": "3448", 
  "blog_bbcode_php": "3397", 
  "blog_comment_profile": "3406", 
  "blog_grouplist": "3452", 
  "cellpadding": "5473", 
  "calendar_smallmonth_week": "4575", 
  "blog_sidebar_user_block_custom": "3502", 
  "blog_sidebar_comment_link": "3494", 
  "blog_list_blogs_blog": "3465", 
  "vbphelper_transaction_bit_3": "5359", 
  "bbcode_html_styleid": -1, 
  "blog_cp_manage_subscriptions_entry": "3422", 
  "EZsociallinks_mitab_data": "835", 
  "forumhome_moderator": "4616", 
  "vbplm_link": "3584", 
  "headinclude": "5525", 
  "showgroups_usergroup": "4843", 
  "EXTRA2": "5472", 
  "bbcode_php_printable": "4546", 
  "calendar_manage": "4557", 
  "blog_sidebar_user_block_comments": "3501", 
  "socialgroups_newgroup_listview_bit": "4890", 
  "spacer_close": "5024", 
  "vbphelper_headinclude_4": "5362", 
  "im_message": "4637", 
  "newreply_reviewbit": "4757", 
  "faqbit_link": "4601", 
  "imgdir_poll": "5483", 
  "postbit": "5510", 
  "help_avatars_avatar": "4622", 
  "subscription_paymentbit": "4911", 
  "blog_navbar_link": "3476", 
  "vbppb_payment_confirmation_textad": "5540", 
  "posticons": "4824", 
  "pm_quickreply": "4789", 
  "album_picturebit": "4529", 
  "modifyusercss": "4723", 
  "textareacols_ns6": "4509", 
  "socialgroups_group": "761", 
  "blog_cp_modify_profile": "3427", 
  "socialgroups_discussionview": "4870", 
  "blog_entry_attachment_image": "3437", 
  "converse": "5004", 
  "codeblockwidth_blog": "3517", 
  "socialgroups_picture": "4893", 
  "modifyprofile_birthday": "4721", 
  "vbppb_main": "5554", 
  "forumrules": "5009", 
  "forumdisplay_changethreadsowner_link": "3598", 
  "blog_grouplist_userbit": "3453", 
  "search_results_postbit": "4839", 
  "socialgroups_managebit": "4881", 
  "subscription_availablebit": "5549", 
  "personal_notepad": "706", 
  "vbppb_": "5530", 
  "visitormessage_preview": "4989", 
  "SHOWTHREAD": "5516", 
  "picturecomment_editor": "4768", 
  "help_bbcodes": "4625", 
  "tag_cloud_box_search": "4922", 
  "htmldoctype": "4490", 
  "userfield_textbox": "4978", 
  "socialgroups_message": "4884", 
  ".fjsel": "639", 
  "ap_groupmessage_ak_bit": "724", 
  "postbit_ignore": "4811", 
  "newthread": "5504", 
  "album_pictureview": "4533", 
  "memberlist_letter": "4683", 
  "post_thanks_postbit": "794", 
  "userfield_radio_option": "4973", 
  "newpost_attachment": "4748", 
  "bbcode_code_styleid": -1, 
  "memberinfo_visitormessage_deleted": "4679", 
  "album_picture_upload": "4536", 
  "ada_postbit_articles": "4273", 
  "usernote_note": "4987", 
  "im_send_aim": "4639", 
  "blog_blog_row": "3400", 
  "vbseo_linkbackbit": "5164", 
  "socialgroups_message_ignored": "4886", 
  "ap_groupmessage_bit": "725", 
  "subscription_payment_alertpay": "4382", 
  "userinfraction_groupbit": "4983", 
  "buddylistbit": "4550", 
  "usercp_groupattentionbit": "4964", 
  "autotag_ajax": "2208", 
  "blog_home_list_comment": "781", 
  "editor_smiliebox_category": "4586", 
  "blog_entry_category": "3439", 
  "blog_entry_deleted": "3440", 
  "newattachment_keybit": "4746", 
  "tag_cloud_link": "4924", 
  "subscribe_showfolders": "4906", 
  "modifyusercss_error": "4727", 
  "im_send_icq": "4640", 
  "memberinfo_block_profilefield": "4657", 
  "subscription_payment_ccbill": "4914", 
  "vbppt_": "5429", 
  "vbphelper_headinclude_3": "5361", 
  "kh99_password_headinc": "5561", 
  "blog_usercp_nav_link": "3515", 
  "socialgroups_transfer": "4900", 
  "blog_list_comments": "3467", 
  "bbcode_html_printable": "4544", 
  "whopostedbit": "4993", 
  "postbit_attachmentmoderated": "4806", 
  "memberlist_results_header": "4686", 
  "vbppb_textad_bit": "5543", 
  "SHOWTHREAD_SHOWPOST": "4849", 
  "reputation_reasonbits": "4835", 
  ".page": "5462", 
  "im_msn": "4638"
}